AStar/__init__.py
AStar/astar.py
AStar/test_astar.py
xhAStar-0.0.2.dist-info/METADATA
xhAStar-0.0.2.dist-info/WHEEL
xhAStar-0.0.2.dist-info/top_level.txt
xhAStar-0.0.2.dist-info/RECORD
