Metadata-Version: 2.1
Name: xhAStar
Version: 0.0.2
Summary: A*搜索算法
Home-page: https://github.com/XHPyPI/AStar
Author: lamborghini1993
Author-email: 1323242382@qq.com
License: UNKNOWN
Platform: UNKNOWN
Classifier: Programming Language :: Python :: 3
Classifier: License :: OSI Approved :: MIT License
Classifier: Operating System :: OS Independent
Requires-Python: >=3.4
